{
	"credit": "Made with Blockbench",
	"parent": "block/thin_block",
	"textures": {
		"particle": "#top"
	},
	"elements": [
		{
			"from": [0, 1, 1.5],
			"to": [1.5, 3.2, 14.5],
			"faces": {
				"east": {"uv": [2, 12.8, 14, 15], "texture": "#side"},
				"west": {"uv": [2, 12.8, 14, 15], "texture": "#side", "cullface": "west"},
				"up": {"uv": [0, 1.5, 1.5, 14.5], "texture": "#trapdoor"},
				"down": {"uv": [0, 1, 1, 15], "texture": "#top", "cullface": "down"}
			}
		},
		{
			"from": [14.5, 1, 1.5],
			"to": [16, 3.2, 14.5],
			"faces": {
				"east": {"uv": [2, 12.8, 14, 15], "texture": "#side", "cullface": "east"},
				"west": {"uv": [2, 12.8, 14, 15], "texture": "#side"},
				"up": {"uv": [14.5, 1.5, 16, 14.5], "texture": "#trapdoor"},
				"down": {"uv": [15, 1, 16, 15], "texture": "#top", "cullface": "down"}
			}
		},
		{
			"from": [0, 1, 0],
			"to": [16, 3.2, 1.5],
			"faces": {
				"north": {"uv": [0, 12.8, 16, 15], "texture": "#side", "cullface": "north"},
				"east": {"uv": [15, 12.8, 16, 15], "texture": "#side", "cullface": "east"},
				"south": {"uv": [0, 12.8, 16, 15], "texture": "#side"},
				"west": {"uv": [0, 12.8, 1, 15], "texture": "#side", "cullface": "west"},
				"up": {"uv": [0, 0, 16, 1.5], "texture": "#trapdoor"},
				"down": {"uv": [0, 15, 16, 16], "texture": "#top", "cullface": "down"}
			}
		},
		{
			"from": [0, 1, 14.5],
			"to": [16, 3.2, 16],
			"faces": {
				"north": {"uv": [0, 12.8, 16, 15], "texture": "#side"},
				"east": {"uv": [0, 12.8, 1, 15], "texture": "#side", "cullface": "east"},
				"south": {"uv": [0, 12.8, 16, 15], "texture": "#side", "cullface": "south"},
				"west": {"uv": [15, 12.8, 16, 15], "texture": "#side", "cullface": "west"},
				"up": {"uv": [0, 14.5, 16, 16], "texture": "#trapdoor"},
				"down": {"uv": [0, 0, 16, 1], "texture": "#top", "cullface": "down"}
			}
		},
		{
			"from": [0, 0, 0],
			"to": [16, 1, 16],
			"faces": {
				"north": {"uv": [0, 15, 16, 16], "texture": "#side", "cullface": "north"},
				"east": {"uv": [0, 15, 16, 16], "texture": "#side", "cullface": "east"},
				"south": {"uv": [0, 15, 16, 16], "texture": "#side", "cullface": "south"},
				"west": {"uv": [0, 15, 16, 16], "texture": "#side", "cullface": "west"},
				"up": {"uv": [0, 0, 16, 16], "texture": "#trapdoor"},
				"down": {"uv": [0, 0, 16, 16], "texture": "#trapdoor", "cullface": "down"}
			}
		},
		{
			"from": [6.5, 1, 1.5],
			"to": [9.5, 3.2, 14.5],
			"faces": {
				"east": {"uv": [1.5, 0, 14.5, 2.2], "texture": "#side"},
				"west": {"uv": [1.5, 0, 14.5, 2.2], "texture": "#side"},
				"up": {"uv": [6.5, 1.5, 9.5, 14.5], "texture": "#trapdoor"}
			}
		},
		{
			"from": [1.5, 1, 6.5],
			"to": [14.5, 3.2, 9.5],
			"rotation": {"angle": 0, "axis": "y", "origin": [8, 2, 8]},
			"faces": {
				"north": {"uv": [1.5, 0, 14.5, 2.2], "texture": "#side"},
				"south": {"uv": [1.5, 0, 14.5, 2.2], "texture": "#side"},
				"up": {"uv": [6.5, 1.5, 9.5, 14.5], "rotation": 270, "texture": "#trapdoor"}
			}
		},
		{
			"name": "1",
			"from": [3.50272, -1.5, 9.5],
			"to": [4.49728, 0, 14.5],
			"rotation": {"angle": 0, "axis": "y", "origin": [4, 5.85, 12]},
			"faces": {
				"north": {"uv": [2, 2, 4, 4], "texture": "#top", "cullface": "down"},
				"south": {"uv": [2, 2, 4, 4], "texture": "#top", "cullface": "down"},
				"down": {"uv": [2, 2, 4, 4], "texture": "#top", "cullface": "down"}
			}
		},
		{
			"name": "2",
			"from": [3.50272, -1.5, 9.5],
			"to": [4.49728, 0, 14.5],
			"rotation": {"angle": 22.5, "axis": "y", "origin": [4, 5.85, 12]},
			"faces": {
				"north": {"uv": [2, 2, 4, 4], "texture": "#top", "cullface": "down"},
				"south": {"uv": [2, 2, 4, 4], "texture": "#top", "cullface": "down"},
				"down": {"uv": [2, 2, 4, 4], "texture": "#top", "cullface": "down"}
			}
		},
		{
			"name": "3",
			"from": [3.50272, -1.5, 9.5],
			"to": [4.49728, 0, 14.5],
			"rotation": {"angle": 45, "axis": "y", "origin": [4, 5.85, 12]},
			"faces": {
				"north": {"uv": [2, 2, 4, 4], "texture": "#top", "cullface": "down"},
				"south": {"uv": [2, 2, 4, 4], "texture": "#top", "cullface": "down"},
				"down": {"uv": [2, 2, 4, 4], "texture": "#top", "cullface": "down"}
			}
		},
		{
			"name": "4",
			"from": [1.5, -1.5, 11.50272],
			"to": [6.5, 0, 12.49728],
			"rotation": {"angle": -22.5, "axis": "y", "origin": [4, 5.85, 12]},
			"faces": {
				"east": {"uv": [2, 2, 4, 4], "texture": "#top", "cullface": "down"},
				"west": {"uv": [2, 2, 4, 4], "texture": "#top", "cullface": "down"},
				"down": {"uv": [2, 2, 4, 4], "texture": "#top", "cullface": "down"}
			}
		},
		{
			"name": "5",
			"from": [1.5, -1.5, 11.50272],
			"to": [6.5, 0, 12.49728],
			"rotation": {"angle": 0, "axis": "y", "origin": [4, 5.85, 12]},
			"faces": {
				"east": {"uv": [2, 2, 4, 4], "texture": "#top", "cullface": "down"},
				"west": {"uv": [2, 2, 4, 4], "texture": "#top", "cullface": "down"},
				"down": {"uv": [2, 2, 4, 4], "texture": "#top", "cullface": "down"}
			}
		},
		{
			"name": "6",
			"from": [1.5, -1.5, 11.50272],
			"to": [6.5, 0, 12.49728],
			"rotation": {"angle": 22.5, "axis": "y", "origin": [4, 5.85, 12]},
			"faces": {
				"east": {"uv": [2, 2, 4, 4], "texture": "#top", "cullface": "down"},
				"west": {"uv": [2, 2, 4, 4], "texture": "#top", "cullface": "down"},
				"down": {"uv": [2, 2, 4, 4], "texture": "#top", "cullface": "down"}
			}
		},
		{
			"name": "7",
			"from": [3.50272, -1.5, 9.5],
			"to": [4.49728, 0, 14.5],
			"rotation": {"angle": -45, "axis": "y", "origin": [4, 5.85, 12]},
			"faces": {
				"north": {"uv": [2, 2, 4, 4], "texture": "#top", "cullface": "down"},
				"south": {"uv": [2, 2, 4, 4], "texture": "#top", "cullface": "down"},
				"down": {"uv": [2, 2, 4, 4], "texture": "#top", "cullface": "down"}
			}
		},
		{
			"name": "8",
			"from": [3.50272, -1.5, 9.5],
			"to": [4.49728, 0, 14.5],
			"rotation": {"angle": -22.5, "axis": "y", "origin": [4, 5.85, 12]},
			"faces": {
				"north": {"uv": [2, 2, 4, 4], "texture": "#top", "cullface": "down"},
				"south": {"uv": [2, 2, 4, 4], "texture": "#top", "cullface": "down"},
				"down": {"uv": [2, 2, 4, 4], "texture": "#top", "cullface": "down"}
			}
		},
		{
			"name": "1",
			"from": [11.50272, -1.5, 9.5],
			"to": [12.49728, 0, 14.5],
			"rotation": {"angle": 0, "axis": "y", "origin": [12, 5.85, 12]},
			"faces": {
				"north": {"uv": [2, 2, 4, 4], "texture": "#top", "cullface": "down"},
				"south": {"uv": [2, 2, 4, 4], "texture": "#top", "cullface": "down"},
				"down": {"uv": [2, 2, 4, 4], "texture": "#top", "cullface": "down"}
			}
		},
		{
			"name": "2",
			"from": [11.50272, -1.5, 9.5],
			"to": [12.49728, 0, 14.5],
			"rotation": {"angle": 22.5, "axis": "y", "origin": [12, 5.85, 12]},
			"faces": {
				"north": {"uv": [2, 2, 4, 4], "texture": "#top", "cullface": "down"},
				"south": {"uv": [2, 2, 4, 4], "texture": "#top", "cullface": "down"},
				"down": {"uv": [2, 2, 4, 4], "texture": "#top", "cullface": "down"}
			}
		},
		{
			"name": "3",
			"from": [11.50272, -1.5, 9.5],
			"to": [12.49728, 0, 14.5],
			"rotation": {"angle": 45, "axis": "y", "origin": [12, 5.85, 12]},
			"faces": {
				"north": {"uv": [2, 2, 4, 4], "texture": "#top", "cullface": "down"},
				"south": {"uv": [2, 2, 4, 4], "texture": "#top", "cullface": "down"},
				"down": {"uv": [2, 2, 4, 4], "texture": "#top", "cullface": "down"}
			}
		},
		{
			"name": "4",
			"from": [9.5, -1.5, 11.50272],
			"to": [14.5, 0, 12.49728],
			"rotation": {"angle": -22.5, "axis": "y", "origin": [12, 5.85, 12]},
			"faces": {
				"east": {"uv": [2, 2, 4, 4], "texture": "#top", "cullface": "down"},
				"west": {"uv": [2, 2, 4, 4], "texture": "#top", "cullface": "down"},
				"down": {"uv": [2, 2, 4, 4], "texture": "#top", "cullface": "down"}
			}
		},
		{
			"name": "5",
			"from": [9.5, -1.5, 11.50272],
			"to": [14.5, 0, 12.49728],
			"rotation": {"angle": 0, "axis": "y", "origin": [12, 5.85, 12]},
			"faces": {
				"east": {"uv": [2, 2, 4, 4], "texture": "#top", "cullface": "down"},
				"west": {"uv": [2, 2, 4, 4], "texture": "#top", "cullface": "down"},
				"down": {"uv": [2, 2, 4, 4], "texture": "#top", "cullface": "down"}
			}
		},
		{
			"name": "6",
			"from": [9.5, -1.5, 11.50272],
			"to": [14.5, 0, 12.49728],
			"rotation": {"angle": 22.5, "axis": "y", "origin": [12, 5.85, 12]},
			"faces": {
				"east": {"uv": [2, 2, 4, 4], "texture": "#top", "cullface": "down"},
				"west": {"uv": [2, 2, 4, 4], "texture": "#top", "cullface": "down"},
				"down": {"uv": [2, 2, 4, 4], "texture": "#top", "cullface": "down"}
			}
		},
		{
			"name": "7",
			"from": [11.50272, -1.5, 9.5],
			"to": [12.49728, 0, 14.5],
			"rotation": {"angle": -45, "axis": "y", "origin": [12, 5.85, 12]},
			"faces": {
				"north": {"uv": [2, 2, 4, 4], "texture": "#top", "cullface": "down"},
				"south": {"uv": [2, 2, 4, 4], "texture": "#top", "cullface": "down"},
				"down": {"uv": [2, 2, 4, 4], "texture": "#top", "cullface": "down"}
			}
		},
		{
			"name": "8",
			"from": [11.50272, -1.5, 9.5],
			"to": [12.49728, 0, 14.5],
			"rotation": {"angle": -22.5, "axis": "y", "origin": [12, 5.85, 12]},
			"faces": {
				"north": {"uv": [2, 2, 4, 4], "texture": "#top", "cullface": "down"},
				"south": {"uv": [2, 2, 4, 4], "texture": "#top", "cullface": "down"},
				"down": {"uv": [2, 2, 4, 4], "texture": "#top", "cullface": "down"}
			}
		},
		{
			"name": "1",
			"from": [3.50272, -1.5, 1.5],
			"to": [4.49728, 0, 6.5],
			"rotation": {"angle": 0, "axis": "y", "origin": [4, 5.85, 4]},
			"faces": {
				"north": {"uv": [2, 2, 4, 4], "texture": "#top", "cullface": "down"},
				"south": {"uv": [2, 2, 4, 4], "texture": "#top", "cullface": "down"},
				"down": {"uv": [2, 2, 4, 4], "texture": "#top", "cullface": "down"}
			}
		},
		{
			"name": "2",
			"from": [3.50272, -1.5, 1.5],
			"to": [4.49728, 0, 6.5],
			"rotation": {"angle": 22.5, "axis": "y", "origin": [4, 5.85, 4]},
			"faces": {
				"north": {"uv": [2, 2, 4, 4], "texture": "#top", "cullface": "down"},
				"south": {"uv": [2, 2, 4, 4], "texture": "#top", "cullface": "down"},
				"down": {"uv": [2, 2, 4, 4], "texture": "#top", "cullface": "down"}
			}
		},
		{
			"name": "3",
			"from": [3.50272, -1.5, 1.5],
			"to": [4.49728, 0, 6.5],
			"rotation": {"angle": 45, "axis": "y", "origin": [4, 5.85, 4]},
			"faces": {
				"north": {"uv": [2, 2, 4, 4], "texture": "#top", "cullface": "down"},
				"south": {"uv": [2, 2, 4, 4], "texture": "#top", "cullface": "down"},
				"down": {"uv": [2, 2, 4, 4], "texture": "#top", "cullface": "down"}
			}
		},
		{
			"name": "4",
			"from": [1.5, -1.5, 3.50272],
			"to": [6.5, 0, 4.49728],
			"rotation": {"angle": -22.5, "axis": "y", "origin": [4, 5.85, 4]},
			"faces": {
				"east": {"uv": [2, 2, 4, 4], "texture": "#top", "cullface": "down"},
				"west": {"uv": [2, 2, 4, 4], "texture": "#top", "cullface": "down"},
				"down": {"uv": [2, 2, 4, 4], "texture": "#top", "cullface": "down"}
			}
		},
		{
			"name": "5",
			"from": [1.5, -1.5, 3.50272],
			"to": [6.5, 0, 4.49728],
			"rotation": {"angle": 0, "axis": "y", "origin": [4, 5.85, 4]},
			"faces": {
				"east": {"uv": [2, 2, 4, 4], "texture": "#top", "cullface": "down"},
				"west": {"uv": [2, 2, 4, 4], "texture": "#top", "cullface": "down"},
				"down": {"uv": [2, 2, 4, 4], "texture": "#top", "cullface": "down"}
			}
		},
		{
			"name": "6",
			"from": [1.5, -1.5, 3.50272],
			"to": [6.5, 0, 4.49728],
			"rotation": {"angle": 22.5, "axis": "y", "origin": [4, 5.85, 4]},
			"faces": {
				"east": {"uv": [2, 2, 4, 4], "texture": "#top", "cullface": "down"},
				"west": {"uv": [2, 2, 4, 4], "texture": "#top", "cullface": "down"},
				"down": {"uv": [2, 2, 4, 4], "texture": "#top", "cullface": "down"}
			}
		},
		{
			"name": "7",
			"from": [3.50272, -1.5, 1.5],
			"to": [4.49728, 0, 6.5],
			"rotation": {"angle": -45, "axis": "y", "origin": [4, 5.85, 4]},
			"faces": {
				"north": {"uv": [2, 2, 4, 4], "texture": "#top", "cullface": "down"},
				"south": {"uv": [2, 2, 4, 4], "texture": "#top", "cullface": "down"},
				"down": {"uv": [2, 2, 4, 4], "texture": "#top", "cullface": "down"}
			}
		},
		{
			"name": "8",
			"from": [3.50272, -1.5, 1.5],
			"to": [4.49728, 0, 6.5],
			"rotation": {"angle": -22.5, "axis": "y", "origin": [4, 5.85, 4]},
			"faces": {
				"north": {"uv": [2, 2, 4, 4], "texture": "#top", "cullface": "down"},
				"south": {"uv": [2, 2, 4, 4], "texture": "#top", "cullface": "down"},
				"down": {"uv": [2, 2, 4, 4], "texture": "#top", "cullface": "down"}
			}
		},
		{
			"name": "1",
			"from": [11.50272, -1.5, 1.5],
			"to": [12.49728, 0, 6.5],
			"rotation": {"angle": 0, "axis": "y", "origin": [12, 5.85, 4]},
			"faces": {
				"north": {"uv": [2, 2, 4, 4], "texture": "#top", "cullface": "down"},
				"south": {"uv": [2, 2, 4, 4], "texture": "#top", "cullface": "down"},
				"down": {"uv": [2, 2, 4, 4], "texture": "#top", "cullface": "down"}
			}
		},
		{
			"name": "2",
			"from": [11.50272, -1.5, 1.5],
			"to": [12.49728, 0, 6.5],
			"rotation": {"angle": 22.5, "axis": "y", "origin": [12, 5.85, 4]},
			"faces": {
				"north": {"uv": [2, 2, 4, 4], "texture": "#top", "cullface": "down"},
				"south": {"uv": [2, 2, 4, 4], "texture": "#top", "cullface": "down"},
				"down": {"uv": [2, 2, 4, 4], "texture": "#top", "cullface": "down"}
			}
		},
		{
			"name": "3",
			"from": [11.50272, -1.5, 1.5],
			"to": [12.49728, 0, 6.5],
			"rotation": {"angle": 45, "axis": "y", "origin": [12, 5.85, 4]},
			"faces": {
				"north": {"uv": [2, 2, 4, 4], "texture": "#top", "cullface": "down"},
				"south": {"uv": [2, 2, 4, 4], "texture": "#top", "cullface": "down"},
				"down": {"uv": [2, 2, 4, 4], "texture": "#top", "cullface": "down"}
			}
		},
		{
			"name": "4",
			"from": [9.5, -1.5, 3.50272],
			"to": [14.5, 0, 4.49728],
			"rotation": {"angle": -22.5, "axis": "y", "origin": [12, 5.85, 4]},
			"faces": {
				"east": {"uv": [2, 2, 4, 4], "texture": "#top", "cullface": "down"},
				"west": {"uv": [2, 2, 4, 4], "texture": "#top", "cullface": "down"},
				"down": {"uv": [2, 2, 4, 4], "texture": "#top", "cullface": "down"}
			}
		},
		{
			"name": "5",
			"from": [9.5, -1.5, 3.50272],
			"to": [14.5, 0, 4.49728],
			"rotation": {"angle": 0, "axis": "y", "origin": [12, 5.85, 4]},
			"faces": {
				"east": {"uv": [2, 2, 4, 4], "texture": "#top", "cullface": "down"},
				"west": {"uv": [2, 2, 4, 4], "texture": "#top", "cullface": "down"},
				"down": {"uv": [2, 2, 4, 4], "texture": "#top", "cullface": "down"}
			}
		},
		{
			"name": "6",
			"from": [9.5, -1.5, 3.50272],
			"to": [14.5, 0, 4.49728],
			"rotation": {"angle": 22.5, "axis": "y", "origin": [12, 5.85, 4]},
			"faces": {
				"east": {"uv": [2, 2, 4, 4], "texture": "#top", "cullface": "down"},
				"west": {"uv": [2, 2, 4, 4], "texture": "#top", "cullface": "down"},
				"down": {"uv": [2, 2, 4, 4], "texture": "#top", "cullface": "down"}
			}
		},
		{
			"name": "7",
			"from": [11.50272, -1.5, 1.5],
			"to": [12.49728, 0, 6.5],
			"rotation": {"angle": -45, "axis": "y", "origin": [12, 5.85, 4]},
			"faces": {
				"north": {"uv": [2, 2, 4, 4], "texture": "#top", "cullface": "down"},
				"south": {"uv": [2, 2, 4, 4], "texture": "#top", "cullface": "down"},
				"down": {"uv": [2, 2, 4, 4], "texture": "#top", "cullface": "down"}
			}
		},
		{
			"name": "8",
			"from": [11.50272, -1.5, 1.5],
			"to": [12.49728, 0, 6.5],
			"rotation": {"angle": -22.5, "axis": "y", "origin": [12, 5.85, 4]},
			"faces": {
				"north": {"uv": [2, 2, 4, 4], "texture": "#top", "cullface": "down"},
				"south": {"uv": [2, 2, 4, 4], "texture": "#top", "cullface": "down"},
				"down": {"uv": [2, 2, 4, 4], "texture": "#top", "cullface": "down"}
			}
		}
	],
	"groups": [
		0,
		1,
		2,
		3,
		4,
		5,
		6,
		{
			"name": "knob",
			"origin": [8, 8, 8],
			"color": 0,
			"children": [7, 8, 9, 10, 11, 12, 13, 14]
		},
		{
			"name": "knob",
			"origin": [8, 8, 8],
			"color": 0,
			"children": [15, 16, 17, 18, 19, 20, 21, 22]
		},
		{
			"name": "knob",
			"origin": [8, 8, 8],
			"color": 0,
			"children": [23, 24, 25, 26, 27, 28, 29, 30]
		},
		{
			"name": "knob",
			"origin": [8, 8, 8],
			"color": 0,
			"children": [31, 32, 33, 34, 35, 36, 37, 38]
		}
	]
}